{
  "animes": [
    {
      "id": 1,
      "title": "Cowboy Bebop",
      "episodes": 26,
      "director": "Shinichiro Watanabe",
      "studio": "Sunrise",
      "img_url": "https://cdn.myanimelist.net/images/anime/4/19644l.jpg"
    },
    {
      "title": "The Tatami Galaxy",
      "episodes": "11",
      "director": "Masaaki Yuasa",
      "studio": "Madhouse",
      "id": 3
    },
    {
      "id": 4,
      "title": "Dear Brother",
      "episodes": 39,
      "director": "Osamu Dezaki",
      "studio": "Tezuka Productions",
      "img_url": "https://cdn.myanimelist.net/images/anime/12/18531l.jpg"
    },
    {
      "title": "Steins;Gate",
      "episodes": "24",
      "director": "Hiroshi Hamasaki",
      "studio": "White Fox",
      "id": 5,
      "img_url": "https://animehunch.com/wp-content/uploads/2020/02/steinsgte.jpg"
    },
    {
      "title": "Sarazanmai",
      "episodes": "11",
      "director": "Kunihiko Ikuhara",
      "studio": "MAPPA",
      "id": 6,
      "img_url": "https://upload.wikimedia.org/wikipedia/en/6/6c/Sarazanmai.animekeyvisual.jpg"
    },
    {
      "title": "Mawaru Penguindrum",
      "episodes": "24",
      "director": "Kunihiko Ikuhara",
      "studio": "Brain's Base",
      "id": 7,
      "img_url": "https://media.kitsu.io/anime/poster_images/6318/large.jpg"
    },
    {
      "title": "Yurikuma Arashi",
      "episodes": "12",
      "director": "Kunihiko Ikuhara",
      "studio": "Silver Link.",
      "id": 8,
      "img_url": "https://i0.hdslb.com/bfs/bangumi/449fec256df0d724d3ff38c784848844e9b1cf26.jpg"
    }
  ]
}